package com.play.live.hqtv;

import java.io.IOException;

public class e
{
  private static final byte[] b;
  private static final byte[] c;
  private static final byte[] d;
  private static final byte[] e;
  private static final byte[] f;
  private static final byte[] g;
  
  static
  {
    boolean bool;
    if (e.class.desiredAssertionStatus()) {
      bool = false;
    } else {
      bool = true;
    }
    a = bool;
    byte[] arrayOfByte = new byte[64];
    arrayOfByte[0] = 65;
    arrayOfByte[1] = 66;
    arrayOfByte[2] = 67;
    arrayOfByte[3] = 68;
    arrayOfByte[4] = 69;
    arrayOfByte[5] = 70;
    arrayOfByte[6] = 71;
    arrayOfByte[7] = 72;
    arrayOfByte[8] = 73;
    arrayOfByte[9] = 74;
    arrayOfByte[10] = 75;
    arrayOfByte[11] = 76;
    arrayOfByte[12] = 77;
    arrayOfByte[13] = 78;
    arrayOfByte[14] = 79;
    arrayOfByte[15] = 80;
    arrayOfByte[16] = 81;
    arrayOfByte[17] = 82;
    arrayOfByte[18] = 83;
    arrayOfByte[19] = 84;
    arrayOfByte[20] = 85;
    arrayOfByte[21] = 86;
    arrayOfByte[22] = 87;
    arrayOfByte[23] = 88;
    arrayOfByte[24] = 89;
    arrayOfByte[25] = 90;
    arrayOfByte[26] = 97;
    arrayOfByte[27] = 98;
    arrayOfByte[28] = 99;
    arrayOfByte[29] = 100;
    arrayOfByte[30] = 101;
    arrayOfByte[31] = 102;
    arrayOfByte[32] = 103;
    arrayOfByte[33] = 104;
    arrayOfByte[34] = 105;
    arrayOfByte[35] = 106;
    arrayOfByte[36] = 107;
    arrayOfByte[37] = 108;
    arrayOfByte[38] = 109;
    arrayOfByte[39] = 110;
    arrayOfByte[40] = 111;
    arrayOfByte[41] = 112;
    arrayOfByte[42] = 113;
    arrayOfByte[43] = 114;
    arrayOfByte[44] = 115;
    arrayOfByte[45] = 116;
    arrayOfByte[46] = 117;
    arrayOfByte[47] = 118;
    arrayOfByte[48] = 119;
    arrayOfByte[49] = 120;
    arrayOfByte[50] = 121;
    arrayOfByte[51] = 122;
    arrayOfByte[52] = 48;
    arrayOfByte[53] = 49;
    arrayOfByte[54] = 50;
    arrayOfByte[55] = 51;
    arrayOfByte[56] = 52;
    arrayOfByte[57] = 53;
    arrayOfByte[58] = 54;
    arrayOfByte[59] = 55;
    arrayOfByte[60] = 56;
    arrayOfByte[61] = 57;
    arrayOfByte[62] = 43;
    arrayOfByte[63] = 47;
    b = arrayOfByte;
    arrayOfByte = new byte[256];
    arrayOfByte[0] = -9;
    arrayOfByte[1] = -9;
    arrayOfByte[2] = -9;
    arrayOfByte[3] = -9;
    arrayOfByte[4] = -9;
    arrayOfByte[5] = -9;
    arrayOfByte[6] = -9;
    arrayOfByte[7] = -9;
    arrayOfByte[8] = -9;
    arrayOfByte[9] = -5;
    arrayOfByte[10] = -5;
    arrayOfByte[11] = -9;
    arrayOfByte[12] = -9;
    arrayOfByte[13] = -5;
    arrayOfByte[14] = -9;
    arrayOfByte[15] = -9;
    arrayOfByte[16] = -9;
    arrayOfByte[17] = -9;
    arrayOfByte[18] = -9;
    arrayOfByte[19] = -9;
    arrayOfByte[20] = -9;
    arrayOfByte[21] = -9;
    arrayOfByte[22] = -9;
    arrayOfByte[23] = -9;
    arrayOfByte[24] = -9;
    arrayOfByte[25] = -9;
    arrayOfByte[26] = -9;
    arrayOfByte[27] = -9;
    arrayOfByte[28] = -9;
    arrayOfByte[29] = -9;
    arrayOfByte[30] = -9;
    arrayOfByte[31] = -9;
    arrayOfByte[32] = -5;
    arrayOfByte[33] = -9;
    arrayOfByte[34] = -9;
    arrayOfByte[35] = -9;
    arrayOfByte[36] = -9;
    arrayOfByte[37] = -9;
    arrayOfByte[38] = -9;
    arrayOfByte[39] = -9;
    arrayOfByte[40] = -9;
    arrayOfByte[41] = -9;
    arrayOfByte[42] = -9;
    arrayOfByte[43] = 62;
    arrayOfByte[44] = -9;
    arrayOfByte[45] = -9;
    arrayOfByte[46] = -9;
    arrayOfByte[47] = 63;
    arrayOfByte[48] = 52;
    arrayOfByte[49] = 53;
    arrayOfByte[50] = 54;
    arrayOfByte[51] = 55;
    arrayOfByte[52] = 56;
    arrayOfByte[53] = 57;
    arrayOfByte[54] = 58;
    arrayOfByte[55] = 59;
    arrayOfByte[56] = 60;
    arrayOfByte[57] = 61;
    arrayOfByte[58] = -9;
    arrayOfByte[59] = -9;
    arrayOfByte[60] = -9;
    arrayOfByte[61] = -1;
    arrayOfByte[62] = -9;
    arrayOfByte[63] = -9;
    arrayOfByte[64] = -9;
    arrayOfByte[66] = 1;
    arrayOfByte[67] = 2;
    arrayOfByte[68] = 3;
    arrayOfByte[69] = 4;
    arrayOfByte[70] = 5;
    arrayOfByte[71] = 6;
    arrayOfByte[72] = 7;
    arrayOfByte[73] = 8;
    arrayOfByte[74] = 9;
    arrayOfByte[75] = 10;
    arrayOfByte[76] = 11;
    arrayOfByte[77] = 12;
    arrayOfByte[78] = 13;
    arrayOfByte[79] = 14;
    arrayOfByte[80] = 15;
    arrayOfByte[81] = 16;
    arrayOfByte[82] = 17;
    arrayOfByte[83] = 18;
    arrayOfByte[84] = 19;
    arrayOfByte[85] = 20;
    arrayOfByte[86] = 21;
    arrayOfByte[87] = 22;
    arrayOfByte[88] = 23;
    arrayOfByte[89] = 24;
    arrayOfByte[90] = 25;
    arrayOfByte[91] = -9;
    arrayOfByte[92] = -9;
    arrayOfByte[93] = -9;
    arrayOfByte[94] = -9;
    arrayOfByte[95] = -9;
    arrayOfByte[96] = -9;
    arrayOfByte[97] = 26;
    arrayOfByte[98] = 27;
    arrayOfByte[99] = 28;
    arrayOfByte[100] = 29;
    arrayOfByte[101] = 30;
    arrayOfByte[102] = 31;
    arrayOfByte[103] = 32;
    arrayOfByte[104] = 33;
    arrayOfByte[105] = 34;
    arrayOfByte[106] = 35;
    arrayOfByte[107] = 36;
    arrayOfByte[108] = 37;
    arrayOfByte[109] = 38;
    arrayOfByte[110] = 39;
    arrayOfByte[111] = 40;
    arrayOfByte[112] = 41;
    arrayOfByte[113] = 42;
    arrayOfByte[114] = 43;
    arrayOfByte[115] = 44;
    arrayOfByte[116] = 45;
    arrayOfByte[117] = 46;
    arrayOfByte[118] = 47;
    arrayOfByte[119] = 48;
    arrayOfByte[120] = 49;
    arrayOfByte[121] = 50;
    arrayOfByte[122] = 51;
    arrayOfByte[123] = -9;
    arrayOfByte[124] = -9;
    arrayOfByte[125] = -9;
    arrayOfByte[126] = -9;
    arrayOfByte[127] = -9;
    arrayOfByte[''] = -9;
    arrayOfByte[''] = -9;
    arrayOfByte[''] = -9;
    arrayOfByte[''] = -9;
    arrayOfByte[''] = -9;
    arrayOfByte[''] = -9;
    arrayOfByte[''] = -9;
    arrayOfByte[''] = -9;
    arrayOfByte[''] = -9;
    arrayOfByte[''] = -9;
    arrayOfByte[''] = -9;
    arrayOfByte[''] = -9;
    arrayOfByte[''] = -9;
    arrayOfByte[''] = -9;
    arrayOfByte[''] = -9;
    arrayOfByte[''] = -9;
    arrayOfByte[''] = -9;
    arrayOfByte[''] = -9;
    arrayOfByte[''] = -9;
    arrayOfByte[''] = -9;
    arrayOfByte[''] = -9;
    arrayOfByte[''] = -9;
    arrayOfByte[''] = -9;
    arrayOfByte[''] = -9;
    arrayOfByte[''] = -9;
    arrayOfByte[''] = -9;
    arrayOfByte[''] = -9;
    arrayOfByte[''] = -9;
    arrayOfByte[''] = -9;
    arrayOfByte[''] = -9;
    arrayOfByte[''] = -9;
    arrayOfByte[''] = -9;
    arrayOfByte[' '] = -9;
    arrayOfByte['¡'] = -9;
    arrayOfByte['¢'] = -9;
    arrayOfByte['£'] = -9;
    arrayOfByte['¤'] = -9;
    arrayOfByte['¥'] = -9;
    arrayOfByte['¦'] = -9;
    arrayOfByte['§'] = -9;
    arrayOfByte['¨'] = -9;
    arrayOfByte['©'] = -9;
    arrayOfByte['ª'] = -9;
    arrayOfByte['«'] = -9;
    arrayOfByte['¬'] = -9;
    arrayOfByte['­'] = -9;
    arrayOfByte['®'] = -9;
    arrayOfByte['¯'] = -9;
    arrayOfByte['°'] = -9;
    arrayOfByte['±'] = -9;
    arrayOfByte['²'] = -9;
    arrayOfByte['³'] = -9;
    arrayOfByte['´'] = -9;
    arrayOfByte['µ'] = -9;
    arrayOfByte['¶'] = -9;
    arrayOfByte['·'] = -9;
    arrayOfByte['¸'] = -9;
    arrayOfByte['¹'] = -9;
    arrayOfByte['º'] = -9;
    arrayOfByte['»'] = -9;
    arrayOfByte['¼'] = -9;
    arrayOfByte['½'] = -9;
    arrayOfByte['¾'] = -9;
    arrayOfByte['¿'] = -9;
    arrayOfByte['À'] = -9;
    arrayOfByte['Á'] = -9;
    arrayOfByte['Â'] = -9;
    arrayOfByte['Ã'] = -9;
    arrayOfByte['Ä'] = -9;
    arrayOfByte['Å'] = -9;
    arrayOfByte['Æ'] = -9;
    arrayOfByte['Ç'] = -9;
    arrayOfByte['È'] = -9;
    arrayOfByte['É'] = -9;
    arrayOfByte['Ê'] = -9;
    arrayOfByte['Ë'] = -9;
    arrayOfByte['Ì'] = -9;
    arrayOfByte['Í'] = -9;
    arrayOfByte['Î'] = -9;
    arrayOfByte['Ï'] = -9;
    arrayOfByte['Ð'] = -9;
    arrayOfByte['Ñ'] = -9;
    arrayOfByte['Ò'] = -9;
    arrayOfByte['Ó'] = -9;
    arrayOfByte['Ô'] = -9;
    arrayOfByte['Õ'] = -9;
    arrayOfByte['Ö'] = -9;
    arrayOfByte['×'] = -9;
    arrayOfByte['Ø'] = -9;
    arrayOfByte['Ù'] = -9;
    arrayOfByte['Ú'] = -9;
    arrayOfByte['Û'] = -9;
    arrayOfByte['Ü'] = -9;
    arrayOfByte['Ý'] = -9;
    arrayOfByte['Þ'] = -9;
    arrayOfByte['ß'] = -9;
    arrayOfByte['à'] = -9;
    arrayOfByte['á'] = -9;
    arrayOfByte['â'] = -9;
    arrayOfByte['ã'] = -9;
    arrayOfByte['ä'] = -9;
    arrayOfByte['å'] = -9;
    arrayOfByte['æ'] = -9;
    arrayOfByte['ç'] = -9;
    arrayOfByte['è'] = -9;
    arrayOfByte['é'] = -9;
    arrayOfByte['ê'] = -9;
    arrayOfByte['ë'] = -9;
    arrayOfByte['ì'] = -9;
    arrayOfByte['í'] = -9;
    arrayOfByte['î'] = -9;
    arrayOfByte['ï'] = -9;
    arrayOfByte['ð'] = -9;
    arrayOfByte['ñ'] = -9;
    arrayOfByte['ò'] = -9;
    arrayOfByte['ó'] = -9;
    arrayOfByte['ô'] = -9;
    arrayOfByte['õ'] = -9;
    arrayOfByte['ö'] = -9;
    arrayOfByte['÷'] = -9;
    arrayOfByte['ø'] = -9;
    arrayOfByte['ù'] = -9;
    arrayOfByte['ú'] = -9;
    arrayOfByte['û'] = -9;
    arrayOfByte['ü'] = -9;
    arrayOfByte['ý'] = -9;
    arrayOfByte['þ'] = -9;
    arrayOfByte['ÿ'] = -9;
    c = arrayOfByte;
    arrayOfByte = new byte[64];
    arrayOfByte[0] = 65;
    arrayOfByte[1] = 66;
    arrayOfByte[2] = 67;
    arrayOfByte[3] = 68;
    arrayOfByte[4] = 69;
    arrayOfByte[5] = 70;
    arrayOfByte[6] = 71;
    arrayOfByte[7] = 72;
    arrayOfByte[8] = 73;
    arrayOfByte[9] = 74;
    arrayOfByte[10] = 75;
    arrayOfByte[11] = 76;
    arrayOfByte[12] = 77;
    arrayOfByte[13] = 78;
    arrayOfByte[14] = 79;
    arrayOfByte[15] = 80;
    arrayOfByte[16] = 81;
    arrayOfByte[17] = 82;
    arrayOfByte[18] = 83;
    arrayOfByte[19] = 84;
    arrayOfByte[20] = 85;
    arrayOfByte[21] = 86;
    arrayOfByte[22] = 87;
    arrayOfByte[23] = 88;
    arrayOfByte[24] = 89;
    arrayOfByte[25] = 90;
    arrayOfByte[26] = 97;
    arrayOfByte[27] = 98;
    arrayOfByte[28] = 99;
    arrayOfByte[29] = 100;
    arrayOfByte[30] = 101;
    arrayOfByte[31] = 102;
    arrayOfByte[32] = 103;
    arrayOfByte[33] = 104;
    arrayOfByte[34] = 105;
    arrayOfByte[35] = 106;
    arrayOfByte[36] = 107;
    arrayOfByte[37] = 108;
    arrayOfByte[38] = 109;
    arrayOfByte[39] = 110;
    arrayOfByte[40] = 111;
    arrayOfByte[41] = 112;
    arrayOfByte[42] = 113;
    arrayOfByte[43] = 114;
    arrayOfByte[44] = 115;
    arrayOfByte[45] = 116;
    arrayOfByte[46] = 117;
    arrayOfByte[47] = 118;
    arrayOfByte[48] = 119;
    arrayOfByte[49] = 120;
    arrayOfByte[50] = 121;
    arrayOfByte[51] = 122;
    arrayOfByte[52] = 48;
    arrayOfByte[53] = 49;
    arrayOfByte[54] = 50;
    arrayOfByte[55] = 51;
    arrayOfByte[56] = 52;
    arrayOfByte[57] = 53;
    arrayOfByte[58] = 54;
    arrayOfByte[59] = 55;
    arrayOfByte[60] = 56;
    arrayOfByte[61] = 57;
    arrayOfByte[62] = 45;
    arrayOfByte[63] = 95;
    d = arrayOfByte;
    arrayOfByte = new byte[256];
    arrayOfByte[0] = -9;
    arrayOfByte[1] = -9;
    arrayOfByte[2] = -9;
    arrayOfByte[3] = -9;
    arrayOfByte[4] = -9;
    arrayOfByte[5] = -9;
    arrayOfByte[6] = -9;
    arrayOfByte[7] = -9;
    arrayOfByte[8] = -9;
    arrayOfByte[9] = -5;
    arrayOfByte[10] = -5;
    arrayOfByte[11] = -9;
    arrayOfByte[12] = -9;
    arrayOfByte[13] = -5;
    arrayOfByte[14] = -9;
    arrayOfByte[15] = -9;
    arrayOfByte[16] = -9;
    arrayOfByte[17] = -9;
    arrayOfByte[18] = -9;
    arrayOfByte[19] = -9;
    arrayOfByte[20] = -9;
    arrayOfByte[21] = -9;
    arrayOfByte[22] = -9;
    arrayOfByte[23] = -9;
    arrayOfByte[24] = -9;
    arrayOfByte[25] = -9;
    arrayOfByte[26] = -9;
    arrayOfByte[27] = -9;
    arrayOfByte[28] = -9;
    arrayOfByte[29] = -9;
    arrayOfByte[30] = -9;
    arrayOfByte[31] = -9;
    arrayOfByte[32] = -5;
    arrayOfByte[33] = -9;
    arrayOfByte[34] = -9;
    arrayOfByte[35] = -9;
    arrayOfByte[36] = -9;
    arrayOfByte[37] = -9;
    arrayOfByte[38] = -9;
    arrayOfByte[39] = -9;
    arrayOfByte[40] = -9;
    arrayOfByte[41] = -9;
    arrayOfByte[42] = -9;
    arrayOfByte[43] = -9;
    arrayOfByte[44] = -9;
    arrayOfByte[45] = 62;
    arrayOfByte[46] = -9;
    arrayOfByte[47] = -9;
    arrayOfByte[48] = 52;
    arrayOfByte[49] = 53;
    arrayOfByte[50] = 54;
    arrayOfByte[51] = 55;
    arrayOfByte[52] = 56;
    arrayOfByte[53] = 57;
    arrayOfByte[54] = 58;
    arrayOfByte[55] = 59;
    arrayOfByte[56] = 60;
    arrayOfByte[57] = 61;
    arrayOfByte[58] = -9;
    arrayOfByte[59] = -9;
    arrayOfByte[60] = -9;
    arrayOfByte[61] = -1;
    arrayOfByte[62] = -9;
    arrayOfByte[63] = -9;
    arrayOfByte[64] = -9;
    arrayOfByte[66] = 1;
    arrayOfByte[67] = 2;
    arrayOfByte[68] = 3;
    arrayOfByte[69] = 4;
    arrayOfByte[70] = 5;
    arrayOfByte[71] = 6;
    arrayOfByte[72] = 7;
    arrayOfByte[73] = 8;
    arrayOfByte[74] = 9;
    arrayOfByte[75] = 10;
    arrayOfByte[76] = 11;
    arrayOfByte[77] = 12;
    arrayOfByte[78] = 13;
    arrayOfByte[79] = 14;
    arrayOfByte[80] = 15;
    arrayOfByte[81] = 16;
    arrayOfByte[82] = 17;
    arrayOfByte[83] = 18;
    arrayOfByte[84] = 19;
    arrayOfByte[85] = 20;
    arrayOfByte[86] = 21;
    arrayOfByte[87] = 22;
    arrayOfByte[88] = 23;
    arrayOfByte[89] = 24;
    arrayOfByte[90] = 25;
    arrayOfByte[91] = -9;
    arrayOfByte[92] = -9;
    arrayOfByte[93] = -9;
    arrayOfByte[94] = -9;
    arrayOfByte[95] = 63;
    arrayOfByte[96] = -9;
    arrayOfByte[97] = 26;
    arrayOfByte[98] = 27;
    arrayOfByte[99] = 28;
    arrayOfByte[100] = 29;
    arrayOfByte[101] = 30;
    arrayOfByte[102] = 31;
    arrayOfByte[103] = 32;
    arrayOfByte[104] = 33;
    arrayOfByte[105] = 34;
    arrayOfByte[106] = 35;
    arrayOfByte[107] = 36;
    arrayOfByte[108] = 37;
    arrayOfByte[109] = 38;
    arrayOfByte[110] = 39;
    arrayOfByte[111] = 40;
    arrayOfByte[112] = 41;
    arrayOfByte[113] = 42;
    arrayOfByte[114] = 43;
    arrayOfByte[115] = 44;
    arrayOfByte[116] = 45;
    arrayOfByte[117] = 46;
    arrayOfByte[118] = 47;
    arrayOfByte[119] = 48;
    arrayOfByte[120] = 49;
    arrayOfByte[121] = 50;
    arrayOfByte[122] = 51;
    arrayOfByte[123] = -9;
    arrayOfByte[124] = -9;
    arrayOfByte[125] = -9;
    arrayOfByte[126] = -9;
    arrayOfByte[127] = -9;
    arrayOfByte[''] = -9;
    arrayOfByte[''] = -9;
    arrayOfByte[''] = -9;
    arrayOfByte[''] = -9;
    arrayOfByte[''] = -9;
    arrayOfByte[''] = -9;
    arrayOfByte[''] = -9;
    arrayOfByte[''] = -9;
    arrayOfByte[''] = -9;
    arrayOfByte[''] = -9;
    arrayOfByte[''] = -9;
    arrayOfByte[''] = -9;
    arrayOfByte[''] = -9;
    arrayOfByte[''] = -9;
    arrayOfByte[''] = -9;
    arrayOfByte[''] = -9;
    arrayOfByte[''] = -9;
    arrayOfByte[''] = -9;
    arrayOfByte[''] = -9;
    arrayOfByte[''] = -9;
    arrayOfByte[''] = -9;
    arrayOfByte[''] = -9;
    arrayOfByte[''] = -9;
    arrayOfByte[''] = -9;
    arrayOfByte[''] = -9;
    arrayOfByte[''] = -9;
    arrayOfByte[''] = -9;
    arrayOfByte[''] = -9;
    arrayOfByte[''] = -9;
    arrayOfByte[''] = -9;
    arrayOfByte[''] = -9;
    arrayOfByte[''] = -9;
    arrayOfByte[' '] = -9;
    arrayOfByte['¡'] = -9;
    arrayOfByte['¢'] = -9;
    arrayOfByte['£'] = -9;
    arrayOfByte['¤'] = -9;
    arrayOfByte['¥'] = -9;
    arrayOfByte['¦'] = -9;
    arrayOfByte['§'] = -9;
    arrayOfByte['¨'] = -9;
    arrayOfByte['©'] = -9;
    arrayOfByte['ª'] = -9;
    arrayOfByte['«'] = -9;
    arrayOfByte['¬'] = -9;
    arrayOfByte['­'] = -9;
    arrayOfByte['®'] = -9;
    arrayOfByte['¯'] = -9;
    arrayOfByte['°'] = -9;
    arrayOfByte['±'] = -9;
    arrayOfByte['²'] = -9;
    arrayOfByte['³'] = -9;
    arrayOfByte['´'] = -9;
    arrayOfByte['µ'] = -9;
    arrayOfByte['¶'] = -9;
    arrayOfByte['·'] = -9;
    arrayOfByte['¸'] = -9;
    arrayOfByte['¹'] = -9;
    arrayOfByte['º'] = -9;
    arrayOfByte['»'] = -9;
    arrayOfByte['¼'] = -9;
    arrayOfByte['½'] = -9;
    arrayOfByte['¾'] = -9;
    arrayOfByte['¿'] = -9;
    arrayOfByte['À'] = -9;
    arrayOfByte['Á'] = -9;
    arrayOfByte['Â'] = -9;
    arrayOfByte['Ã'] = -9;
    arrayOfByte['Ä'] = -9;
    arrayOfByte['Å'] = -9;
    arrayOfByte['Æ'] = -9;
    arrayOfByte['Ç'] = -9;
    arrayOfByte['È'] = -9;
    arrayOfByte['É'] = -9;
    arrayOfByte['Ê'] = -9;
    arrayOfByte['Ë'] = -9;
    arrayOfByte['Ì'] = -9;
    arrayOfByte['Í'] = -9;
    arrayOfByte['Î'] = -9;
    arrayOfByte['Ï'] = -9;
    arrayOfByte['Ð'] = -9;
    arrayOfByte['Ñ'] = -9;
    arrayOfByte['Ò'] = -9;
    arrayOfByte['Ó'] = -9;
    arrayOfByte['Ô'] = -9;
    arrayOfByte['Õ'] = -9;
    arrayOfByte['Ö'] = -9;
    arrayOfByte['×'] = -9;
    arrayOfByte['Ø'] = -9;
    arrayOfByte['Ù'] = -9;
    arrayOfByte['Ú'] = -9;
    arrayOfByte['Û'] = -9;
    arrayOfByte['Ü'] = -9;
    arrayOfByte['Ý'] = -9;
    arrayOfByte['Þ'] = -9;
    arrayOfByte['ß'] = -9;
    arrayOfByte['à'] = -9;
    arrayOfByte['á'] = -9;
    arrayOfByte['â'] = -9;
    arrayOfByte['ã'] = -9;
    arrayOfByte['ä'] = -9;
    arrayOfByte['å'] = -9;
    arrayOfByte['æ'] = -9;
    arrayOfByte['ç'] = -9;
    arrayOfByte['è'] = -9;
    arrayOfByte['é'] = -9;
    arrayOfByte['ê'] = -9;
    arrayOfByte['ë'] = -9;
    arrayOfByte['ì'] = -9;
    arrayOfByte['í'] = -9;
    arrayOfByte['î'] = -9;
    arrayOfByte['ï'] = -9;
    arrayOfByte['ð'] = -9;
    arrayOfByte['ñ'] = -9;
    arrayOfByte['ò'] = -9;
    arrayOfByte['ó'] = -9;
    arrayOfByte['ô'] = -9;
    arrayOfByte['õ'] = -9;
    arrayOfByte['ö'] = -9;
    arrayOfByte['÷'] = -9;
    arrayOfByte['ø'] = -9;
    arrayOfByte['ù'] = -9;
    arrayOfByte['ú'] = -9;
    arrayOfByte['û'] = -9;
    arrayOfByte['ü'] = -9;
    arrayOfByte['ý'] = -9;
    arrayOfByte['þ'] = -9;
    arrayOfByte['ÿ'] = -9;
    e = arrayOfByte;
    arrayOfByte = new byte[64];
    arrayOfByte[0] = 45;
    arrayOfByte[1] = 48;
    arrayOfByte[2] = 49;
    arrayOfByte[3] = 50;
    arrayOfByte[4] = 51;
    arrayOfByte[5] = 52;
    arrayOfByte[6] = 53;
    arrayOfByte[7] = 54;
    arrayOfByte[8] = 55;
    arrayOfByte[9] = 56;
    arrayOfByte[10] = 57;
    arrayOfByte[11] = 65;
    arrayOfByte[12] = 66;
    arrayOfByte[13] = 67;
    arrayOfByte[14] = 68;
    arrayOfByte[15] = 69;
    arrayOfByte[16] = 70;
    arrayOfByte[17] = 71;
    arrayOfByte[18] = 72;
    arrayOfByte[19] = 73;
    arrayOfByte[20] = 74;
    arrayOfByte[21] = 75;
    arrayOfByte[22] = 76;
    arrayOfByte[23] = 77;
    arrayOfByte[24] = 78;
    arrayOfByte[25] = 79;
    arrayOfByte[26] = 80;
    arrayOfByte[27] = 81;
    arrayOfByte[28] = 82;
    arrayOfByte[29] = 83;
    arrayOfByte[30] = 84;
    arrayOfByte[31] = 85;
    arrayOfByte[32] = 86;
    arrayOfByte[33] = 87;
    arrayOfByte[34] = 88;
    arrayOfByte[35] = 89;
    arrayOfByte[36] = 90;
    arrayOfByte[37] = 95;
    arrayOfByte[38] = 97;
    arrayOfByte[39] = 98;
    arrayOfByte[40] = 99;
    arrayOfByte[41] = 100;
    arrayOfByte[42] = 101;
    arrayOfByte[43] = 102;
    arrayOfByte[44] = 103;
    arrayOfByte[45] = 104;
    arrayOfByte[46] = 105;
    arrayOfByte[47] = 106;
    arrayOfByte[48] = 107;
    arrayOfByte[49] = 108;
    arrayOfByte[50] = 109;
    arrayOfByte[51] = 110;
    arrayOfByte[52] = 111;
    arrayOfByte[53] = 112;
    arrayOfByte[54] = 113;
    arrayOfByte[55] = 114;
    arrayOfByte[56] = 115;
    arrayOfByte[57] = 116;
    arrayOfByte[58] = 117;
    arrayOfByte[59] = 118;
    arrayOfByte[60] = 119;
    arrayOfByte[61] = 120;
    arrayOfByte[62] = 121;
    arrayOfByte[63] = 122;
    f = arrayOfByte;
    arrayOfByte = new byte[257];
    arrayOfByte[0] = -9;
    arrayOfByte[1] = -9;
    arrayOfByte[2] = -9;
    arrayOfByte[3] = -9;
    arrayOfByte[4] = -9;
    arrayOfByte[5] = -9;
    arrayOfByte[6] = -9;
    arrayOfByte[7] = -9;
    arrayOfByte[8] = -9;
    arrayOfByte[9] = -5;
    arrayOfByte[10] = -5;
    arrayOfByte[11] = -9;
    arrayOfByte[12] = -9;
    arrayOfByte[13] = -5;
    arrayOfByte[14] = -9;
    arrayOfByte[15] = -9;
    arrayOfByte[16] = -9;
    arrayOfByte[17] = -9;
    arrayOfByte[18] = -9;
    arrayOfByte[19] = -9;
    arrayOfByte[20] = -9;
    arrayOfByte[21] = -9;
    arrayOfByte[22] = -9;
    arrayOfByte[23] = -9;
    arrayOfByte[24] = -9;
    arrayOfByte[25] = -9;
    arrayOfByte[26] = -9;
    arrayOfByte[27] = -9;
    arrayOfByte[28] = -9;
    arrayOfByte[29] = -9;
    arrayOfByte[30] = -9;
    arrayOfByte[31] = -9;
    arrayOfByte[32] = -5;
    arrayOfByte[33] = -9;
    arrayOfByte[34] = -9;
    arrayOfByte[35] = -9;
    arrayOfByte[36] = -9;
    arrayOfByte[37] = -9;
    arrayOfByte[38] = -9;
    arrayOfByte[39] = -9;
    arrayOfByte[40] = -9;
    arrayOfByte[41] = -9;
    arrayOfByte[42] = -9;
    arrayOfByte[43] = -9;
    arrayOfByte[44] = -9;
    arrayOfByte[46] = -9;
    arrayOfByte[47] = -9;
    arrayOfByte[48] = 1;
    arrayOfByte[49] = 2;
    arrayOfByte[50] = 3;
    arrayOfByte[51] = 4;
    arrayOfByte[52] = 5;
    arrayOfByte[53] = 6;
    arrayOfByte[54] = 7;
    arrayOfByte[55] = 8;
    arrayOfByte[56] = 9;
    arrayOfByte[57] = 10;
    arrayOfByte[58] = -9;
    arrayOfByte[59] = -9;
    arrayOfByte[60] = -9;
    arrayOfByte[61] = -1;
    arrayOfByte[62] = -9;
    arrayOfByte[63] = -9;
    arrayOfByte[64] = -9;
    arrayOfByte[65] = 11;
    arrayOfByte[66] = 12;
    arrayOfByte[67] = 13;
    arrayOfByte[68] = 14;
    arrayOfByte[69] = 15;
    arrayOfByte[70] = 16;
    arrayOfByte[71] = 17;
    arrayOfByte[72] = 18;
    arrayOfByte[73] = 19;
    arrayOfByte[74] = 20;
    arrayOfByte[75] = 21;
    arrayOfByte[76] = 22;
    arrayOfByte[77] = 23;
    arrayOfByte[78] = 24;
    arrayOfByte[79] = 25;
    arrayOfByte[80] = 26;
    arrayOfByte[81] = 27;
    arrayOfByte[82] = 28;
    arrayOfByte[83] = 29;
    arrayOfByte[84] = 30;
    arrayOfByte[85] = 31;
    arrayOfByte[86] = 32;
    arrayOfByte[87] = 33;
    arrayOfByte[88] = 34;
    arrayOfByte[89] = 35;
    arrayOfByte[90] = 36;
    arrayOfByte[91] = -9;
    arrayOfByte[92] = -9;
    arrayOfByte[93] = -9;
    arrayOfByte[94] = -9;
    arrayOfByte[95] = 37;
    arrayOfByte[96] = -9;
    arrayOfByte[97] = 38;
    arrayOfByte[98] = 39;
    arrayOfByte[99] = 40;
    arrayOfByte[100] = 41;
    arrayOfByte[101] = 42;
    arrayOfByte[102] = 43;
    arrayOfByte[103] = 44;
    arrayOfByte[104] = 45;
    arrayOfByte[105] = 46;
    arrayOfByte[106] = 47;
    arrayOfByte[107] = 48;
    arrayOfByte[108] = 49;
    arrayOfByte[109] = 50;
    arrayOfByte[110] = 51;
    arrayOfByte[111] = 52;
    arrayOfByte[112] = 53;
    arrayOfByte[113] = 54;
    arrayOfByte[114] = 55;
    arrayOfByte[115] = 56;
    arrayOfByte[116] = 57;
    arrayOfByte[117] = 58;
    arrayOfByte[118] = 59;
    arrayOfByte[119] = 60;
    arrayOfByte[120] = 61;
    arrayOfByte[121] = 62;
    arrayOfByte[122] = 63;
    arrayOfByte[123] = -9;
    arrayOfByte[124] = -9;
    arrayOfByte[125] = -9;
    arrayOfByte[126] = -9;
    arrayOfByte[127] = -9;
    arrayOfByte[''] = -9;
    arrayOfByte[''] = -9;
    arrayOfByte[''] = -9;
    arrayOfByte[''] = -9;
    arrayOfByte[''] = -9;
    arrayOfByte[''] = -9;
    arrayOfByte[''] = -9;
    arrayOfByte[''] = -9;
    arrayOfByte[''] = -9;
    arrayOfByte[''] = -9;
    arrayOfByte[''] = -9;
    arrayOfByte[''] = -9;
    arrayOfByte[''] = -9;
    arrayOfByte[''] = -9;
    arrayOfByte[''] = -9;
    arrayOfByte[''] = -9;
    arrayOfByte[''] = -9;
    arrayOfByte[''] = -9;
    arrayOfByte[''] = -9;
    arrayOfByte[''] = -9;
    arrayOfByte[''] = -9;
    arrayOfByte[''] = -9;
    arrayOfByte[''] = -9;
    arrayOfByte[''] = -9;
    arrayOfByte[''] = -9;
    arrayOfByte[''] = -9;
    arrayOfByte[''] = -9;
    arrayOfByte[''] = -9;
    arrayOfByte[''] = -9;
    arrayOfByte[''] = -9;
    arrayOfByte[''] = -9;
    arrayOfByte[''] = -9;
    arrayOfByte[' '] = -9;
    arrayOfByte['¡'] = -9;
    arrayOfByte['¢'] = -9;
    arrayOfByte['£'] = -9;
    arrayOfByte['¤'] = -9;
    arrayOfByte['¥'] = -9;
    arrayOfByte['¦'] = -9;
    arrayOfByte['§'] = -9;
    arrayOfByte['¨'] = -9;
    arrayOfByte['©'] = -9;
    arrayOfByte['ª'] = -9;
    arrayOfByte['«'] = -9;
    arrayOfByte['¬'] = -9;
    arrayOfByte['­'] = -9;
    arrayOfByte['®'] = -9;
    arrayOfByte['¯'] = -9;
    arrayOfByte['°'] = -9;
    arrayOfByte['±'] = -9;
    arrayOfByte['²'] = -9;
    arrayOfByte['³'] = -9;
    arrayOfByte['´'] = -9;
    arrayOfByte['µ'] = -9;
    arrayOfByte['¶'] = -9;
    arrayOfByte['·'] = -9;
    arrayOfByte['¸'] = -9;
    arrayOfByte['¹'] = -9;
    arrayOfByte['º'] = -9;
    arrayOfByte['»'] = -9;
    arrayOfByte['¼'] = -9;
    arrayOfByte['½'] = -9;
    arrayOfByte['¾'] = -9;
    arrayOfByte['¿'] = -9;
    arrayOfByte['À'] = -9;
    arrayOfByte['Á'] = -9;
    arrayOfByte['Â'] = -9;
    arrayOfByte['Ã'] = -9;
    arrayOfByte['Ä'] = -9;
    arrayOfByte['Å'] = -9;
    arrayOfByte['Æ'] = -9;
    arrayOfByte['Ç'] = -9;
    arrayOfByte['È'] = -9;
    arrayOfByte['É'] = -9;
    arrayOfByte['Ê'] = -9;
    arrayOfByte['Ë'] = -9;
    arrayOfByte['Ì'] = -9;
    arrayOfByte['Í'] = -9;
    arrayOfByte['Î'] = -9;
    arrayOfByte['Ï'] = -9;
    arrayOfByte['Ð'] = -9;
    arrayOfByte['Ñ'] = -9;
    arrayOfByte['Ò'] = -9;
    arrayOfByte['Ó'] = -9;
    arrayOfByte['Ô'] = -9;
    arrayOfByte['Õ'] = -9;
    arrayOfByte['Ö'] = -9;
    arrayOfByte['×'] = -9;
    arrayOfByte['Ø'] = -9;
    arrayOfByte['Ù'] = -9;
    arrayOfByte['Ú'] = -9;
    arrayOfByte['Û'] = -9;
    arrayOfByte['Ü'] = -9;
    arrayOfByte['Ý'] = -9;
    arrayOfByte['Þ'] = -9;
    arrayOfByte['ß'] = -9;
    arrayOfByte['à'] = -9;
    arrayOfByte['á'] = -9;
    arrayOfByte['â'] = -9;
    arrayOfByte['ã'] = -9;
    arrayOfByte['ä'] = -9;
    arrayOfByte['å'] = -9;
    arrayOfByte['æ'] = -9;
    arrayOfByte['ç'] = -9;
    arrayOfByte['è'] = -9;
    arrayOfByte['é'] = -9;
    arrayOfByte['ê'] = -9;
    arrayOfByte['ë'] = -9;
    arrayOfByte['ì'] = -9;
    arrayOfByte['í'] = -9;
    arrayOfByte['î'] = -9;
    arrayOfByte['ï'] = -9;
    arrayOfByte['ð'] = -9;
    arrayOfByte['ñ'] = -9;
    arrayOfByte['ò'] = -9;
    arrayOfByte['ó'] = -9;
    arrayOfByte['ô'] = -9;
    arrayOfByte['õ'] = -9;
    arrayOfByte['ö'] = -9;
    arrayOfByte['÷'] = -9;
    arrayOfByte['ø'] = -9;
    arrayOfByte['ù'] = -9;
    arrayOfByte['ú'] = -9;
    arrayOfByte['û'] = -9;
    arrayOfByte['ü'] = -9;
    arrayOfByte['ý'] = -9;
    arrayOfByte['þ'] = -9;
    arrayOfByte['ÿ'] = -9;
    arrayOfByte[256] = -9;
    g = arrayOfByte;
  }
  
  private static int a(byte[] paramArrayOfByte1, int paramInt1, byte[] paramArrayOfByte2, int paramInt2, int paramInt3)
  {
    int i = 1;
    if (paramArrayOfByte1 != null)
    {
      if (paramArrayOfByte2 != null)
      {
        if ((paramInt1 >= 0) && (paramInt1 + 3 < paramArrayOfByte1.length))
        {
          if ((paramInt2 >= 0) && (paramInt2 + 2 < paramArrayOfByte2.length))
          {
            localObject = a(paramInt3);
            if (paramArrayOfByte1[(paramInt1 + 2)] != 61)
            {
              if (paramArrayOfByte1[(paramInt1 + 3)] != 61)
              {
                i = (0xFF & localObject[paramArrayOfByte1[paramInt1]]) << 18 | (0xFF & localObject[paramArrayOfByte1[(paramInt1 + 1)]]) << 12 | (0xFF & localObject[paramArrayOfByte1[(paramInt1 + 2)]]) << 6 | 0xFF & localObject[paramArrayOfByte1[(paramInt1 + 3)]];
                paramArrayOfByte2[paramInt2] = ((byte)(i >> 16));
                paramArrayOfByte2[(paramInt2 + 1)] = ((byte)(i >> 8));
                paramArrayOfByte2[(paramInt2 + 2)] = ((byte)i);
                i = 3;
              }
              else
              {
                i = (0xFF & localObject[paramArrayOfByte1[paramInt1]]) << 18 | (0xFF & localObject[paramArrayOfByte1[(paramInt1 + 1)]]) << 12 | (0xFF & localObject[paramArrayOfByte1[(paramInt1 + 2)]]) << 6;
                paramArrayOfByte2[paramInt2] = ((byte)(i >>> 16));
                paramArrayOfByte2[(paramInt2 + 1)] = ((byte)(i >>> 8));
                i = 2;
              }
            }
            else {
              paramArrayOfByte2[paramInt2] = ((byte)(((0xFF & localObject[paramArrayOfByte1[paramInt1]]) << 18 | (0xFF & localObject[paramArrayOfByte1[(paramInt1 + 1)]]) << 12) >>> 16));
            }
            return i;
          }
          localObject = new Object[2];
          localObject[0] = Integer.valueOf(paramArrayOfByte2.length);
          localObject[i] = Integer.valueOf(paramInt2);
          throw new IllegalArgumentException(String.format("Destination array with length %d cannot have offset of %d and still store three bytes.", (Object[])localObject));
        }
        Object localObject = new Object[2];
        localObject[0] = Integer.valueOf(paramArrayOfByte1.length);
        localObject[i] = Integer.valueOf(paramInt1);
        throw new IllegalArgumentException(String.format("Source array with length %d cannot have offset of %d and still process four bytes.", (Object[])localObject));
      }
      throw new NullPointerException("Destination array was null.");
    }
    throw new NullPointerException("Source array was null.");
  }
  
  private static final byte[] a(int paramInt)
  {
    byte[] arrayOfByte;
    if ((paramInt & 0x10) != 16)
    {
      if ((paramInt & 0x20) != 32) {
        arrayOfByte = c;
      } else {
        arrayOfByte = g;
      }
    }
    else {
      arrayOfByte = e;
    }
    return arrayOfByte;
  }
  
  public static byte[] a(String paramString)
  {
    return a(paramString, 0);
  }
  
  /* Error */
  public static byte[] a(String paramString, int paramInt)
  {
    // Byte code:
    //   0: aconst_null
    //   1: astore_2
    //   2: aload_0
    //   3: ifnonnull +13 -> 16
    //   6: new 131	java/lang/NullPointerException
    //   9: dup
    //   10: ldc 148
    //   12: invokespecial 134	java/lang/NullPointerException:<init>	(Ljava/lang/String;)V
    //   15: athrow
    //   16: aload_0
    //   17: ldc 150
    //   19: invokevirtual 153	java/lang/String:getBytes	(Ljava/lang/String;)[B
    //   22: astore_3
    //   23: aload_3
    //   24: astore_3
    //   25: aload_3
    //   26: iconst_0
    //   27: aload_3
    //   28: arraylength
    //   29: iload_1
    //   30: invokestatic 156	com/play/live/hqtv/e:a	([BIII)[B
    //   33: astore 4
    //   35: iload_1
    //   36: iconst_4
    //   37: iand
    //   38: ifeq +129 -> 167
    //   41: iconst_1
    //   42: istore_3
    //   43: aload 4
    //   45: ifnull +110 -> 155
    //   48: aload 4
    //   50: arraylength
    //   51: iconst_4
    //   52: if_icmplt +103 -> 155
    //   55: iload_3
    //   56: ifne +99 -> 155
    //   59: ldc 157
    //   61: sipush 255
    //   64: aload 4
    //   66: iconst_0
    //   67: baload
    //   68: iand
    //   69: ldc 158
    //   71: aload 4
    //   73: iconst_1
    //   74: baload
    //   75: bipush 8
    //   77: ishl
    //   78: iand
    //   79: ior
    //   80: if_icmpne +75 -> 155
    //   83: sipush 2048
    //   86: newarray byte
    //   88: astore 6
    //   90: new 160	java/io/ByteArrayOutputStream
    //   93: dup
    //   94: invokespecial 161	java/io/ByteArrayOutputStream:<init>	()V
    //   97: astore_3
    //   98: new 163	java/io/ByteArrayInputStream
    //   101: dup
    //   102: aload 4
    //   104: invokespecial 166	java/io/ByteArrayInputStream:<init>	([B)V
    //   107: astore 5
    //   109: new 168	java/util/zip/GZIPInputStream
    //   112: dup
    //   113: aload 5
    //   115: invokespecial 171	java/util/zip/GZIPInputStream:<init>	(Ljava/io/InputStream;)V
    //   118: astore_2
    //   119: aload_2
    //   120: aload 6
    //   122: invokevirtual 175	java/util/zip/GZIPInputStream:read	([B)I
    //   125: istore 7
    //   127: iload 7
    //   129: ifge +43 -> 172
    //   132: aload_3
    //   133: invokevirtual 179	java/io/ByteArrayOutputStream:toByteArray	()[B
    //   136: astore 4
    //   138: aload 4
    //   140: astore 4
    //   142: aload_3
    //   143: invokevirtual 182	java/io/ByteArrayOutputStream:close	()V
    //   146: aload_2
    //   147: invokevirtual 183	java/util/zip/GZIPInputStream:close	()V
    //   150: aload 5
    //   152: invokevirtual 184	java/io/ByteArrayInputStream:close	()V
    //   155: aload 4
    //   157: areturn
    //   158: pop
    //   159: aload_0
    //   160: invokevirtual 186	java/lang/String:getBytes	()[B
    //   163: astore_3
    //   164: goto -139 -> 25
    //   167: iconst_0
    //   168: istore_3
    //   169: goto -126 -> 43
    //   172: aload_3
    //   173: aload 6
    //   175: iconst_0
    //   176: iload 7
    //   178: invokevirtual 190	java/io/ByteArrayOutputStream:write	([BII)V
    //   181: goto -62 -> 119
    //   184: astore 6
    //   186: aload_2
    //   187: astore_2
    //   188: aload 5
    //   190: astore 5
    //   192: ldc 192
    //   194: new 194	java/lang/StringBuilder
    //   197: dup
    //   198: ldc 196
    //   200: invokespecial 197	java/lang/StringBuilder:<init>	(Ljava/lang/String;)V
    //   203: aload 6
    //   205: invokevirtual 201	java/io/IOException:getMessage	()Ljava/lang/String;
    //   208: invokevirtual 205	java/lang/StringBuilder:append	(Ljava/lang/String;)Ljava/lang/StringBuilder;
    //   211: invokevirtual 208	java/lang/StringBuilder:toString	()Ljava/lang/String;
    //   214: invokestatic 213	android/util/Log:e	(Ljava/lang/String;Ljava/lang/String;)I
    //   217: pop
    //   218: aload_3
    //   219: invokevirtual 182	java/io/ByteArrayOutputStream:close	()V
    //   222: aload_2
    //   223: invokevirtual 183	java/util/zip/GZIPInputStream:close	()V
    //   226: aload 5
    //   228: invokevirtual 184	java/io/ByteArrayInputStream:close	()V
    //   231: goto -76 -> 155
    //   234: pop
    //   235: goto -80 -> 155
    //   238: astore 4
    //   240: aconst_null
    //   241: astore_3
    //   242: aconst_null
    //   243: astore 5
    //   245: aload_3
    //   246: invokevirtual 182	java/io/ByteArrayOutputStream:close	()V
    //   249: aload_2
    //   250: invokevirtual 183	java/util/zip/GZIPInputStream:close	()V
    //   253: aload 5
    //   255: invokevirtual 184	java/io/ByteArrayInputStream:close	()V
    //   258: aload 4
    //   260: athrow
    //   261: pop
    //   262: goto -40 -> 222
    //   265: pop
    //   266: goto -40 -> 226
    //   269: pop
    //   270: goto -21 -> 249
    //   273: pop
    //   274: goto -21 -> 253
    //   277: pop
    //   278: goto -20 -> 258
    //   281: pop
    //   282: goto -136 -> 146
    //   285: pop
    //   286: goto -136 -> 150
    //   289: pop
    //   290: goto -135 -> 155
    //   293: astore 4
    //   295: aconst_null
    //   296: astore 5
    //   298: goto -53 -> 245
    //   301: astore 4
    //   303: aload 5
    //   305: astore 5
    //   307: goto -62 -> 245
    //   310: astore 4
    //   312: aload_2
    //   313: astore_2
    //   314: aload 5
    //   316: astore 5
    //   318: goto -73 -> 245
    //   321: astore 4
    //   323: goto -78 -> 245
    //   326: astore 6
    //   328: aconst_null
    //   329: astore_3
    //   330: aconst_null
    //   331: astore 5
    //   333: goto -141 -> 192
    //   336: astore 6
    //   338: aconst_null
    //   339: astore 5
    //   341: goto -149 -> 192
    //   344: astore 6
    //   346: aload 5
    //   348: astore 5
    //   350: goto -158 -> 192
    // Local variable table:
    //   start	length	slot	name	signature
    //   0	353	0	paramString	String
    //   0	353	1	paramInt	int
    //   1	313	2	localGZIPInputStream	java.util.zip.GZIPInputStream
    //   22	6	3	arrayOfByte1	byte[]
    //   42	14	3	i	int
    //   97	67	3	localObject1	Object
    //   168	51	3	j	int
    //   241	89	3	localObject2	Object
    //   33	123	4	arrayOfByte2	byte[]
    //   238	21	4	localObject3	Object
    //   293	1	4	localObject4	Object
    //   301	1	4	localObject5	Object
    //   310	1	4	localObject6	Object
    //   321	1	4	localObject7	Object
    //   107	242	5	localByteArrayInputStream	java.io.ByteArrayInputStream
    //   88	86	6	arrayOfByte3	byte[]
    //   184	20	6	localIOException1	IOException
    //   326	1	6	localIOException2	IOException
    //   336	1	6	localIOException3	IOException
    //   344	1	6	localIOException4	IOException
    //   125	52	7	k	int
    //   158	1	21	localUnsupportedEncodingException	java.io.UnsupportedEncodingException
    //   234	1	22	localException1	java.lang.Exception
    //   261	1	23	localException2	java.lang.Exception
    //   265	1	24	localException3	java.lang.Exception
    //   269	1	25	localException4	java.lang.Exception
    //   273	1	26	localException5	java.lang.Exception
    //   277	1	27	localException6	java.lang.Exception
    //   281	1	28	localException7	java.lang.Exception
    //   285	1	29	localException8	java.lang.Exception
    //   289	1	30	localException9	java.lang.Exception
    // Exception table:
    //   from	to	target	type
    //   16	23	158	java/io/UnsupportedEncodingException
    //   119	138	184	java/io/IOException
    //   172	181	184	java/io/IOException
    //   226	231	234	java/lang/Exception
    //   90	98	238	finally
    //   218	222	261	java/lang/Exception
    //   222	226	265	java/lang/Exception
    //   245	249	269	java/lang/Exception
    //   249	253	273	java/lang/Exception
    //   253	258	277	java/lang/Exception
    //   142	146	281	java/lang/Exception
    //   146	150	285	java/lang/Exception
    //   150	155	289	java/lang/Exception
    //   98	109	293	finally
    //   109	119	301	finally
    //   119	138	310	finally
    //   172	181	310	finally
    //   192	218	321	finally
    //   90	98	326	java/io/IOException
    //   98	109	336	java/io/IOException
    //   109	119	344	java/io/IOException
  }
  
  public static byte[] a(byte[] paramArrayOfByte, int paramInt1, int paramInt2, int paramInt3)
  {
    if (paramArrayOfByte != null)
    {
      if ((paramInt1 >= 0) && (paramInt1 + paramInt2 <= paramArrayOfByte.length))
      {
        if (paramInt2 != 0)
        {
          if (paramInt2 >= 4)
          {
            byte[] arrayOfByte1 = a(paramInt3);
            Object localObject2 = new byte[paramInt2 * 3 / 4];
            byte[] arrayOfByte2 = new byte[4];
            int i = paramInt1;
            int m = 0;
            int k = 0;
            while (i < paramInt1 + paramInt2)
            {
              j = arrayOfByte1[(0xFF & paramArrayOfByte[i])];
              if (j < -5)
              {
                localObject2 = new Object[2];
                localObject2[0] = Integer.valueOf(0xFF & paramArrayOfByte[i]);
                localObject2[1] = Integer.valueOf(i);
                throw new IOException(String.format("Bad Base64 input character decimal %d in array position %d", (Object[])localObject2));
              }
              if (j < -1)
              {
                j = m;
                k = k;
              }
              else
              {
                j = m + 1;
                arrayOfByte2[m] = paramArrayOfByte[i];
                if (j <= 3)
                {
                  k = k;
                }
                else
                {
                  j = k + a(arrayOfByte2, 0, (byte[])localObject2, k, paramInt3);
                  if (paramArrayOfByte[i] == 61) {
                    break label223;
                  }
                  k = j;
                  j = 0;
                }
              }
              i++;
              k = k;
              m = j;
            }
            int j = k;
            label223:
            localObject1 = new byte[j];
            System.arraycopy(localObject2, 0, localObject1, 0, j);
            localObject1 = localObject1;
          }
          else
          {
            throw new IllegalArgumentException("Base64-encoded string must have at least four characters, but length specified was " + paramInt2);
          }
        }
        else {
          localObject1 = new byte[0];
        }
        return localObject1;
      }
      Object localObject1 = new Object[3];
      localObject1[0] = Integer.valueOf(paramArrayOfByte.length);
      localObject1[1] = Integer.valueOf(paramInt1);
      localObject1[2] = Integer.valueOf(paramInt2);
      throw new IllegalArgumentException(String.format("Source array with length %d cannot have offset of %d and process %d bytes.", (Object[])localObject1));
    }
    throw new NullPointerException("Cannot decode null source array.");
  }
}


/* Location:           C:\Users\PJ\Desktop\get-apk-source_win\classes_dex2jar.jar
 * Qualified Name:     com.play.live.hqtv.e
 * JD-Core Version:    0.7.0.1
 */